Metadata-Version: 2.1
Name: tptp
Version: 0.0.3.dev2
Summary: A library for handling TPTP related input and systems
Home-page: https://github.com/leoprover/tptp
Author: Tobias Gleißner
Author-email: tobias.gleissner@fu-berlin.de
License: BSD3
Platform: UNKNOWN
Classifier: Development Status :: 2 - Pre-Alpha
Classifier: Environment :: Console
Classifier: Environment :: Web Environment
Classifier: Intended Audience :: Developers
Classifier: Intended Audience :: Education
Classifier: Intended Audience :: Information Technology
Classifier: Intended Audience :: Legal Industry
Classifier: Intended Audience :: Science/Research
Classifier: Topic :: Scientific/Engineering :: Artificial Intelligence
Classifier: Programming Language :: Python :: 3.5
Classifier: Programming Language :: Python :: 3.6
Classifier: Programming Language :: Python :: 3.7
Classifier: Programming Language :: Python :: 3.8
Classifier: Programming Language :: Python :: 3.9
Requires-Python: >=3.5
Requires-Dist: pathlib
Requires-Dist: lxml
Requires-Dist: requests
Requires-Dist: colorama
